[
  {
    "reportid":"49426",
    "misperid":"9039",
    "initial_risk_level":"High",
    "current_final_risk_level":"High",
    "forenames":"Thomas",
    "surname":"Wood",
    "dob":"2014-12-07",
    "pob":"Lancaster",
    "age":"5",
    "sex":"Male",
    "residence_type":"Home Address",
    "occdesc":"",
    "nominalpersionid":"3496",
    "missing_since":"2020-09-12 00:00:00",
    "date_reported_missing":"2020-09-12 04:00:00",
    "day_reported_missing":"Saturday",
    "length_missing_mins":"4372",
    "when_traced":"2020-09-15 00:52:00",
    "mf_address":"312 Greengairs Road, Greengairs, ML6 7TQ",
    "missing_from":"Home",
    "reported_missing_by":"Derek Wilson",
    "TL_address":"1-42 West Lodge Gardens, Alloa, FK10 2HX",
    "return_method_desc":"Traced by family"
  },
  {
    "reportid":"247",
    "misperid":"9039",
    "initial_risk_level":"Medium",
    "current_final_risk_level":"Low",
    "forenames":"Thomas",
    "surname":"Wood",
    "dob":"2014-12-07",
    "pob":"Lancaster",
    "age":"5",
    "sex":"Male",
    "residence_type":"Home Address",
    "occdesc":"",
    "nominalpersionid":"3496",
    "missing_since":"2020-10-21 00:52:00",
    "date_reported_missing":"2020-10-21 00:52:00",
    "day_reported_missing":"Wednesday",
    "length_missing_mins":"723",
    "when_traced":"2020-10-21 12:55:00",
    "mf_address":"1G Bank Street,  EH39 4NY",
    "missing_from":"movie theater",
    "reported_missing_by":"Antony Bradshaw",
    "TL_address":"24-28 Torphichen Street, Edinburgh, EH3 8JB",
    "return_method_desc":"Traced by Police"
  },
  {
    "reportid":"32954",
    "misperid":"9039",
    "initial_risk_level":"High",
    "current_final_risk_level":"High",
    "forenames":"Thomas",
    "surname":"Wood",
    "dob":"2014-12-07",
    "pob":"Lancaster",
    "age":"6",
    "sex":"Male",
    "residence_type":"Home Address",
    "occdesc":"",
    "nominalpersionid":"3496",
    "missing_since":"2020-12-12 12:55:00",
    "date_reported_missing":"2020-12-13 00:55:00",
    "day_reported_missing":"Sunday",
    "length_missing_mins":"3195",
    "when_traced":"2020-12-14 18:10:00",
    "mf_address":"312 Greengairs Road, Greengairs, ML6 7TQ",
    "missing_from":"Home",
    "reported_missing_by":"Dawn Parkes",
    "TL_address":"1-42 West Lodge Gardens, Alloa, FK10 2HX",
    "return_method_desc":"Traced by Police"
  },
  {
    "reportid":"96560",
    "misperid":"9039",
    "initial_risk_level":"High",
    "current_final_risk_level":"High",
    "forenames":"Thomas",
    "surname":"Wood",
    "dob":"2014-12-07",
    "pob":"Lancaster",
    "age":"6",
    "sex":"Male",
    "residence_type":"Home Address",
    "occdesc":"",
    "nominalpersionid":"3496",
    "missing_since":"2021-05-24 18:10:00",
    "date_reported_missing":"2021-05-26 04:10:00",
    "day_reported_missing":"Wednesday",
    "length_missing_mins":"3469",
    "when_traced":"2021-05-27 03:59:00",
    "mf_address":"312 Greengairs Road, Greengairs, ML6 7TQ",
    "missing_from":"Home",
    "reported_missing_by":"Dawn Parkes",
    "TL_address":"Hyndford Street, Dundee, DD2 1HQ",
    "return_method_desc":"Traced by Police"
  },
  {
    "reportid":"96459",
    "misperid":"9039",
    "initial_risk_level":"Medium",
    "current_final_risk_level":"Medium",
    "forenames":"Thomas",
    "surname":"Wood",
    "dob":"2014-12-07",
    "pob":"Lancaster",
    "age":"6",
    "sex":"Male",
    "residence_type":"Home Address",
    "occdesc":"",
    "nominalpersionid":"3496",
    "missing_since":"2021-08-13 03:59:00",
    "date_reported_missing":"2021-08-13 13:59:00",
    "day_reported_missing":"Friday",
    "length_missing_mins":"6282",
    "when_traced":"2021-08-17 12:41:00",
    "mf_address":"312 Greengairs Road, Greengairs, ML6 7TQ",
    "missing_from":"Home",
    "reported_missing_by":"Donald Thornton",
    "TL_address":"6 Lownie Road, Forfar, DD8 2RT",
    "return_method_desc":"Traced by staff"
  },
  {
    "reportid":"47966",
    "misperid":"9039",
    "initial_risk_level":"High",
    "current_final_risk_level":"High",
    "forenames":"Thomas",
    "surname":"Wood",
    "dob":"2014-12-07",
    "pob":"Lancaster",
    "age":"6",
    "sex":"Male",
    "residence_type":"Home Address",
    "occdesc":"",
    "nominalpersionid":"3496",
    "missing_since":"2021-11-21 12:41:00",
    "date_reported_missing":"2021-11-21 17:41:00",
    "day_reported_missing":"Sunday",
    "length_missing_mins":"5019",
    "when_traced":"2021-11-25 00:20:00",
    "mf_address":"312 Greengairs Road, Greengairs, ML6 7TQ",
    "missing_from":"Home",
    "reported_missing_by":"Derek Wilson",
    "TL_address":"Park Mains, Erskine, PA8 7AL",
    "return_method_desc":"Traced by Police"
  },
  {
    "reportid":"25099",
    "misperid":"9039",
    "initial_risk_level":"Medium",
    "current_final_risk_level":"Medium",
    "forenames":"Thomas",
    "surname":"Wood",
    "dob":"2014-12-07",
    "pob":"Lancaster",
    "age":"7",
    "sex":"Male",
    "residence_type":"Home Address",
    "occdesc":"",
    "nominalpersionid":"3496",
    "missing_since":"2022-03-21 00:20:00",
    "date_reported_missing":"2022-03-21 04:20:00",
    "day_reported_missing":"Monday",
    "length_missing_mins":"577",
    "when_traced":"2022-03-21 09:57:00",
    "mf_address":"312 Greengairs Road, Greengairs, ML6 7TQ",
    "missing_from":"Home",
    "reported_missing_by":"Antony Bradshaw",
    "TL_address":"1-42 West Lodge Gardens, Alloa, FK10 2HX",
    "return_method_desc":"Traced by Police"
  },
  {
    "reportid":"91789",
    "misperid":"9039",
    "initial_risk_level":"Low",
    "current_final_risk_level":"Low",
    "forenames":"Thomas",
    "surname":"Wood",
    "dob":"2014-12-07",
    "pob":"Lancaster",
    "age":"7",
    "sex":"Male",
    "residence_type":"Home Address",
    "occdesc":"",
    "nominalpersionid":"3496",
    "missing_since":"2022-06-08 09:57:00",
    "date_reported_missing":"2022-06-08 17:57:00",
    "day_reported_missing":"Wednesday",
    "length_missing_mins":"5134",
    "when_traced":"2022-06-11 23:31:00",
    "mf_address":"312 Greengairs Road, Greengairs, ML6 7TQ",
    "missing_from":"Home",
    "reported_missing_by":"Antony Bradshaw",
    "TL_address":"36-42 Watson Avenue, St Andrews, KY16 8JE",
    "return_method_desc":"Traced by Police"
  },
  {
    "reportid":"43523",
    "misperid":"9039",
    "initial_risk_level":"High",
    "current_final_risk_level":"High",
    "forenames":"Thomas",
    "surname":"Wood",
    "dob":"2014-12-07",
    "pob":"Lancaster",
    "age":"7",
    "sex":"Male",
    "residence_type":"Home Address",
    "occdesc":"",
    "nominalpersionid":"3496",
    "missing_since":"2022-08-02 23:31:00",
    "date_reported_missing":"2022-08-04 13:31:00",
    "day_reported_missing":"Thursday",
    "length_missing_mins":"3657",
    "when_traced":"2022-08-05 12:28:00",
    "mf_address":"312 Greengairs Road, Greengairs, ML6 7TQ",
    "missing_from":"Home",
    "reported_missing_by":"Sara Thomas",
    "TL_address":"24-28 Torphichen Street, Edinburgh, EH3 8JB",
    "return_method_desc":"Traced by Police"
  },
  {
    "reportid":"86021",
    "misperid":"9039",
    "initial_risk_level":"Medium",
    "current_final_risk_level":"Medium",
    "forenames":"Thomas",
    "surname":"Wood",
    "dob":"2014-12-07",
    "pob":"Lancaster",
    "age":"7",
    "sex":"Male",
    "residence_type":"Home Address",
    "occdesc":"",
    "nominalpersionid":"3496",
    "missing_since":"2022-12-02 12:28:00",
    "date_reported_missing":"2022-12-03 00:28:00",
    "day_reported_missing":"Saturday",
    "length_missing_mins":"4768",
    "when_traced":"2022-12-05 19:56:00",
    "mf_address":"312 Greengairs Road, Greengairs, ML6 7TQ",
    "missing_from":"Home",
    "reported_missing_by":"Antony Bradshaw",
    "TL_address":"312 Greengairs Road, Greengairs, ML6 7TQ",
    "return_method_desc":"Traced by Police"
  },
  {
    "reportid":"87889",
    "misperid":"9039",
    "initial_risk_level":"Medium",
    "current_final_risk_level":"Medium",
    "forenames":"Thomas",
    "surname":"Wood",
    "dob":"2014-12-07",
    "pob":"Lancaster",
    "age":"8",
    "sex":"Male",
    "residence_type":"Home Address",
    "occdesc":"",
    "nominalpersionid":"3496",
    "missing_since":"2023-05-22 19:56:00",
    "date_reported_missing":"2023-05-23 20:56:00",
    "day_reported_missing":"Tuesday",
    "length_missing_mins":"1971",
    "when_traced":"2023-05-24 04:47:00",
    "mf_address":"312 Greengairs Road, Greengairs, ML6 7TQ",
    "missing_from":"Home",
    "reported_missing_by":"Derek Wilson",
    "TL_address":"Ness Walk, Inverness, IV3 5SF",
    "return_method_desc":"Traced by family"
  },
  {
    "reportid":"58266",
    "misperid":"9039",
    "initial_risk_level":"High",
    "current_final_risk_level":"High",
    "forenames":"Thomas",
    "surname":"Wood",
    "dob":"2014-12-07",
    "pob":"Lancaster",
    "age":"8",
    "sex":"Male",
    "residence_type":"Home Address",
    "occdesc":"",
    "nominalpersionid":"3496",
    "missing_since":"2023-11-15 04:47:00",
    "date_reported_missing":"2023-11-15 04:47:00",
    "day_reported_missing":"Wednesday",
    "length_missing_mins":"9073",
    "when_traced":"2023-11-21 12:00:00",
    "mf_address":"312 Greengairs Road, Greengairs, ML6 7TQ",
    "missing_from":"Home",
    "reported_missing_by":"Georgina Kennedy",
    "TL_address":"36-42 Watson Avenue, St Andrews, KY16 8JE",
    "return_method_desc":"Traced by Police"
  },
  {
    "reportid":"68259",
    "misperid":"9039",
    "initial_risk_level":"Medium",
    "current_final_risk_level":"Medium",
    "forenames":"Thomas",
    "surname":"Wood",
    "dob":"2014-12-07",
    "pob":"Lancaster",
    "age":"9",
    "sex":"Male",
    "residence_type":"Home Address",
    "occdesc":"",
    "nominalpersionid":"3496",
    "missing_since":"2024-01-17 12:00:00",
    "date_reported_missing":"2024-01-17 12:00:00",
    "day_reported_missing":"Wednesday",
    "length_missing_mins":"355",
    "when_traced":"2024-01-17 17:55:00",
    "mf_address":"312 Greengairs Road, Greengairs, ML6 7TQ",
    "missing_from":"Home",
    "reported_missing_by":"Dawn Parkes",
    "TL_address":"Hyndford Street, Dundee, DD2 1HQ",
    "return_method_desc":"Traced by family"
  },
  {
    "reportid":"38511",
    "misperid":"9039",
    "initial_risk_level":"Low",
    "current_final_risk_level":"Low",
    "forenames":"Thomas",
    "surname":"Wood",
    "dob":"2014-12-07",
    "pob":"Lancaster",
    "age":"9",
    "sex":"Male",
    "residence_type":"Home Address",
    "occdesc":"",
    "nominalpersionid":"3496",
    "missing_since":"2024-06-15 17:55:00",
    "date_reported_missing":"2024-06-16 01:55:00",
    "day_reported_missing":"Sunday",
    "length_missing_mins":"5010",
    "when_traced":"2024-06-19 05:25:00",
    "mf_address":"312 Greengairs Road, Greengairs, ML6 7TQ",
    "missing_from":"Home",
    "reported_missing_by":"Dawn Parkes",
    "TL_address":"312 Greengairs Road, Greengairs, ML6 7TQ",
    "return_method_desc":"Traced by staff"
  },
  {
    "reportid":"21810",
    "misperid":"9039",
    "initial_risk_level":"High",
    "current_final_risk_level":"High",
    "forenames":"Thomas",
    "surname":"Wood",
    "dob":"2014-12-07",
    "pob":"Lancaster",
    "age":"9",
    "sex":"Male",
    "residence_type":"Home Address",
    "occdesc":"",
    "nominalpersionid":"3496",
    "missing_since":"2024-07-14 05:25:00",
    "date_reported_missing":"2024-07-14 15:25:00",
    "day_reported_missing":"Sunday",
    "length_missing_mins":"6599",
    "when_traced":"2024-07-18 19:24:00",
    "mf_address":"312 Greengairs Road, Greengairs, ML6 7TQ",
    "missing_from":"Home",
    "reported_missing_by":"Derek Wilson",
    "TL_address":"1-42 West Lodge Gardens, Alloa, FK10 2HX",
    "return_method_desc":"Traced by Police"
  },
  {
    "reportid":"93973",
    "misperid":"9039",
    "initial_risk_level":"High",
    "current_final_risk_level":"High",
    "forenames":"Thomas",
    "surname":"Wood",
    "dob":"2014-12-07",
    "pob":"Lancaster",
    "age":"9",
    "sex":"Male",
    "residence_type":"Home Address",
    "occdesc":"",
    "nominalpersionid":"3496",
    "missing_since":"2024-11-15 19:24:00",
    "date_reported_missing":"2024-11-15 23:24:00",
    "day_reported_missing":"Friday",
    "length_missing_mins":"571",
    "when_traced":"2024-11-16 04:55:00",
    "mf_address":"312 Greengairs Road, Greengairs, ML6 7TQ",
    "missing_from":"Home",
    "reported_missing_by":"Derek Wilson",
    "TL_address":"Hyndford Street, Dundee, DD2 1HQ",
    "return_method_desc":"Traced by Police"
  },
  {
    "reportid":"10726",
    "misperid":"9039",
    "initial_risk_level":"Medium",
    "current_final_risk_level":"Medium",
    "forenames":"Thomas",
    "surname":"Wood",
    "dob":"2014-12-07",
    "pob":"Lancaster",
    "age":"9",
    "sex":"Male",
    "residence_type":"Home Address",
    "occdesc":"",
    "nominalpersionid":"3496",
    "missing_since":"2024-11-21 04:55:00",
    "date_reported_missing":"2024-11-22 03:55:00",
    "day_reported_missing":"Friday",
    "length_missing_mins":"2633",
    "when_traced":"2024-11-23 00:48:00",
    "mf_address":"312 Greengairs Road, Greengairs, ML6 7TQ",
    "missing_from":"Home",
    "reported_missing_by":"Donald Thornton",
    "TL_address":"312 Greengairs Road, Greengairs, ML6 7TQ",
    "return_method_desc":"Traced by Police"
  },
  {
    "reportid":"29433",
    "misperid":"9039",
    "initial_risk_level":"Medium",
    "current_final_risk_level":"Medium",
    "forenames":"Thomas",
    "surname":"Wood",
    "dob":"2014-12-07",
    "pob":"Lancaster",
    "age":"10",
    "sex":"Male",
    "residence_type":"Home Address",
    "occdesc":"",
    "nominalpersionid":"3496",
    "missing_since":"2025-01-05 00:48:00",
    "date_reported_missing":"2025-01-05 00:48:00",
    "day_reported_missing":"Sunday",
    "length_missing_mins":"355",
    "when_traced":"2025-01-05 06:43:00",
    "mf_address":"312 Greengairs Road, Greengairs, ML6 7TQ",
    "missing_from":"Home",
    "reported_missing_by":"Sara Thomas",
    "TL_address":"Hyndford Street, Dundee, DD2 1HQ",
    "return_method_desc":"Traced by Police"
  },
  {
    "reportid":"53485",
    "misperid":"9039",
    "initial_risk_level":"Low",
    "current_final_risk_level":"Low",
    "forenames":"Thomas",
    "surname":"Wood",
    "dob":"2014-12-07",
    "pob":"Lancaster",
    "age":"10",
    "sex":"Male",
    "residence_type":"Home Address",
    "occdesc":"",
    "nominalpersionid":"3496",
    "missing_since":"2025-02-07 06:43:00",
    "date_reported_missing":"2025-02-08 05:43:00",
    "day_reported_missing":"Saturday",
    "length_missing_mins":"7632",
    "when_traced":"2025-02-12 13:55:00",
    "mf_address":"312 Greengairs Road, Greengairs, ML6 7TQ",
    "missing_from":"Home",
    "reported_missing_by":"Dawn Parkes",
    "TL_address":"24-28 Torphichen Street, Edinburgh, EH3 8JB",
    "return_method_desc":"Traced by Police"
  },
  {
    "reportid":"8772",
    "misperid":"9039",
    "initial_risk_level":"High",
    "current_final_risk_level":"High",
    "forenames":"Thomas",
    "surname":"Wood",
    "dob":"2014-12-07",
    "pob":"Lancaster",
    "age":"10",
    "sex":"Male",
    "residence_type":"Home Address",
    "occdesc":"",
    "nominalpersionid":"3496",
    "missing_since":"2025-05-23 13:55:00",
    "date_reported_missing":"2025-05-23 15:55:00",
    "day_reported_missing":"Friday",
    "length_missing_mins":"4324",
    "when_traced":"2025-05-26 13:59:00",
    "mf_address":"312 Greengairs Road, Greengairs, ML6 7TQ",
    "missing_from":"Home",
    "reported_missing_by":"Derek Wilson",
    "TL_address":"Ness Walk, Inverness, IV3 5SF",
    "return_method_desc":"Traced by Police"
  },
  {
    "reportid":"65422",
    "misperid":"9039",
    "initial_risk_level":"Low",
    "current_final_risk_level":"Low",
    "forenames":"Thomas",
    "surname":"Wood",
    "dob":"2014-12-07",
    "pob":"Lancaster",
    "age":"10",
    "sex":"Male",
    "residence_type":"Home Address",
    "occdesc":"",
    "nominalpersionid":"3496",
    "missing_since":"2025-07-02 13:59:00",
    "date_reported_missing":"2025-07-03 01:59:00",
    "day_reported_missing":"Thursday",
    "length_missing_mins":"8184",
    "when_traced":"2025-07-08 06:23:00",
    "mf_address":"312 Greengairs Road, Greengairs, ML6 7TQ",
    "missing_from":"Home",
    "reported_missing_by":"Sara Thomas",
    "TL_address":"Dirleton Road,  EH39 5DF",
    "return_method_desc":"Traced by Police"
  }
]