{
    "forenames": "Mark",
    "surname": "Johnson",
    "maidenname": "",
    "nickname": "PaleVioletRed",
    "misperid": 8154,
    "nominalid": 23,
    "sex": "Male",
    "date_of_birth": "1978-01-31",
    "age": 47,
    "foster care": false,
    "child_protection": false,
    "ethnical_appearance": "Black Caribbean",
    "person_language": "English",
    "place_of_birth": "Newcastle-upon-Tyne",
    "disability_status": "Yes (please specify)",
    "disability_desc": "Hearing Impairment",
    "occupation": "Software engineer",
    "reports_starting_from": "2025-01-09",
    "addresses": [
        {
            "address": "312 Greengairs Road, Greengairs, ML6 7TQ",
            "type": "Home"
        },
        {
            "address": "17,18 Dundurn Walk,  PH6 2NA",
            "type": "medical appointments"
        }
    ],
    "traced_locations": [
        "312 Greengairs Road, Greengairs, ML6 7TQ",
        "296A Strathmore Avenue, Dundee, DD3 6SH",
        "115-125 Walker Drive, South Queensferry, EH30 9XJ",
        "8 Camdean Lane, Rosyth, KY11 2TA",
        "1 Dick Place, Rosyth, KY11 2JG",
        "16 Spylaw Bank Road, Edinburgh, EH13 0JW",
        "Gallanach Road,  PA34 4PE",
        "Kenilworth Drive,  FK2 9LH",
        "1 Alloway Place, Dundee, DD4 8UA",
        "55 Eastfield, Edinburgh, EH15 2PJ",
        "23a Rosebery Avenue, South Queensferry, EH30 9JG"
    ],
    "people_reporting": [
        "Maurice Johnson",
        "Kenneth Barber",
        "Stephen West",
        "Francis Johnston",
        "Joanne Gardiner",
        "Shane Lewis",
        "Allan Warren"
    ]
}